py_resources_vickodev/__init__.py
py_resources_vickodev/main.py
py_resources_vickodev-0.1.1.dist-info/WHEEL
py_resources_vickodev-0.1.1.dist-info/METADATA
py_resources_vickodev-0.1.1.dist-info/RECORD
