Metadata-Version: 2.3
Name: py-resources_vickodev
Version: 0.1.1
Summary: A message resources lightweight package for Python applications like i18n.
Author: Victor A Higuita
Author-email: Victor A Higuita <harvic3@proton.me>
License: MIT
Classifier: Programming Language :: Python :: 3.12
Classifier: License :: OSI Approved :: MIT License
Classifier: Operating System :: OS Independent
Requires-Python: >=3.12
Project-URL: Documentation, https://github.com/harvic3/py-tools/py-resources/README.md
Project-URL: Homepage, https://github.com/harvic3/py-tools/py-resources
Project-URL: Issues, https://github.com/harvic3/py-tools/py-resources/issues
Project-URL: Repository, https://github.com/harvic3/py-tools/py-resources
